api/__init__.py
api/admin.py
api/apps.py
api/health.py
api/models.py
api/tests.py
api/urls.py
api/views.py
api/migrations/__init__.py
dictionary/__init__.py
dictionary/admin.py
dictionary/apps.py
dictionary/models.py
dictionary/replacement.py
dictionary/tests.py
dictionary/urls.py
dictionary/views.py
dictionary/management/__init__.py
dictionary/management/commands/__init__.py
dictionary/management/commands/add_entry.py
dictionary/management/commands/replace_text.py
dictionary/migrations/0001_initial.py
dictionary/migrations/0002_categorysuggestion.py
dictionary/migrations/0003_delete_categorysuggestion.py
dictionary/migrations/__init__.py
dictionary/templates/dictionary/home.html
dictionary/templates/dictionary/replace.html
iir/__init__.py
iir/__main__.py
iir/cli.py
iir_tool-0.2.0.dist-info/licenses/LICENSE
mcp/__init__.py
mcp/admin.py
mcp/apps.py
mcp/models.py
mcp/tests.py
mcp/urls.py
mcp/views.py
svr/__init__.py
svr/asgi.py
svr/settings.py
svr/urls.py
svr/wsgi.py
iir_tool-0.2.0.dist-info/METADATA
iir_tool-0.2.0.dist-info/WHEEL
iir_tool-0.2.0.dist-info/entry_points.txt
iir_tool-0.2.0.dist-info/top_level.txt
iir_tool-0.2.0.dist-info/RECORD
