Metadata-Version: 2.4
Name: iir-tool
Version: 0.2.0
Summary: Internal Info Replacement CLI
Project-URL: Homepage, https://github.com/koich-min/iir
Project-URL: Repository, https://github.com/koich-min/iir
Project-URL: Issues, https://github.com/koich-min/iir/issues
Requires-Python: >=3.12
License-File: LICENSE
Requires-Dist: Django==6.0
Requires-Dist: djangorestframework==3.16.1
Requires-Dist: uvicorn>=0.30
Requires-Dist: whitenoise>=6.0
Provides-Extra: postgres
Requires-Dist: psycopg2>=2.9; extra == "postgres"
Provides-Extra: mysql
Requires-Dist: mysqlclient>=2.2; extra == "mysql"
Dynamic: license-file
